pycognitocli/__init__.py
pycognitocli/console.py
pycognitocli/py.typed
pycognitocli-0.3.2.dist-info/entry_points.txt
pycognitocli-0.3.2.dist-info/LICENSE
pycognitocli-0.3.2.dist-info/WHEEL
pycognitocli-0.3.2.dist-info/METADATA
pycognitocli-0.3.2.dist-info/RECORD
