Metadata-Version: 2.1
Name: pycognitocli
Version: 0.3.2
Summary: CLI for https://pypi.org/project/pycognito/
Home-page: https://gitlab.com/advian-oss/python-pycognitocli/
License: MIT
Author: Eero af Heurlin
Author-email: eero.afheurlin@advian.fi
Requires-Python: >=3.8,<4.0
Classifier: License :: OSI Approved :: MIT License
Classifier: Programming Language :: Python :: 3
Classifier: Programming Language :: Python :: 3.10
Classifier: Programming Language :: Python :: 3.8
Classifier: Programming Language :: Python :: 3.9
Requires-Dist: click (>=8.0,<9.0)
Requires-Dist: libadvian (>=1.0,<2.0)
Requires-Dist: pycognito (>=2021.3,<2022.0)
Project-URL: Repository, https://gitlab.com/advian-oss/python-pycognitocli/
